dollar_yen/__init__.py
dollar_yen/main.py
dollar_yen-0.0.2.dist-info/LICENCE
dollar_yen-0.0.2.dist-info/METADATA
dollar_yen-0.0.2.dist-info/WHEEL
dollar_yen-0.0.2.dist-info/entry_points.txt
dollar_yen-0.0.2.dist-info/top_level.txt
dollar_yen-0.0.2.dist-info/RECORD
