Metadata-Version: 2.1
Name: dollar-yen
Version: 0.0.2
Summary: Convert dollars to yen.
Home-page: https://github.com/spc-nmurata/dollar-yen
Author: naoyuki murata
Author-email: nmurata@sciencepark.co.jp
License: UNKNOWN
Project-URL: Bug Tracker, https://github.com/spc-nmurata/dollar-yen
Platform: UNKNOWN
Classifier: Programming Language :: Python :: 3
Classifier: License :: OSI Approved :: MIT License
Classifier: Operating System :: OS Independent
Requires-Python: >=3.8
License-File: LICENCE
Requires-Dist: multitasking
Requires-Dist: yfinance
